sockschain/__init__.py
sockschain/__main__.py
GreenPonikSocksipyChain-2.1.2.dist-info/LICENSE
GreenPonikSocksipyChain-2.1.2.dist-info/METADATA
GreenPonikSocksipyChain-2.1.2.dist-info/WHEEL
GreenPonikSocksipyChain-2.1.2.dist-info/entry_points.txt
GreenPonikSocksipyChain-2.1.2.dist-info/top_level.txt
GreenPonikSocksipyChain-2.1.2.dist-info/RECORD
