Metadata-Version: 2.1
Name: GreenPonikSocksipyChain
Version: 2.1.2
Summary: A Python SOCKS/HTTP Proxy module
Home-page: https://github.com/GreenPonik/PySocksipyChain
Author: Bjarni R. Einarsson
Author-email: bre@pagekite.net
License: BSD
Project-URL: Source, https://github.com/pagekite/PySocksipyChain
Project-URL: Bug Reports, https://github.com/pagekite/PySocksipyChain/issues
Platform: UNKNOWN
License-File: LICENSE
Requires-Dist: six
